{
    "avatarId": "SL341747",
    "avatarName": "SL 341747",
    "avatarSize": 100,
    "animationsGenerated": {
        "idle": {
            "idle": {
                "enabled": true,
                "isLoop": true,
                "probability": 1000,
                "finalFileName": "idle.gif",
                "packedFileName": "341729.gif",
                "uploadId": 341729,
                "uploadTime": "20080917155617",
                "uploadUserId": 93135,
                "uploadSize": 2788,
                "uploadUrl": "http://files.zweitgeist.com/60/a9/19/0aa932d7dc1e19490d7e6461f5702ca43e.gif"
            },
            "hands": {
                "enabled": true,
                "isLoop": false,
                "probability": 5,
                "finalFileName": "idle-hands.gif",
                "packedFileName": "341730.gif",
                "uploadId": 341730,
                "uploadTime": "20080917155622",
                "uploadUserId": 93135,
                "uploadSize": 62827,
                "uploadUrl": "http://files.zweitgeist.com/21/60/18/ea2c96fefb863ff1f7db7ab94dde563eee.gif"
            },
            "lookleft": {
                "enabled": true,
                "isLoop": false,
                "probability": 5,
                "finalFileName": "idle-lookleft.gif",
                "packedFileName": "341731.gif",
                "uploadId": 341731,
                "uploadTime": "20080917155626",
                "uploadUserId": 93135,
                "uploadSize": 71979,
                "uploadUrl": "http://files.zweitgeist.com/41/66/a3/f836c210498f81772a5d0718978f2f591a.gif"
            },
            "lookright": {
                "enabled": true,
                "isLoop": false,
                "probability": 5,
                "finalFileName": "idle-lookright.gif",
                "packedFileName": "341732.gif",
                "uploadId": 341732,
                "uploadTime": "20080917155630",
                "uploadUserId": 93135,
                "uploadSize": 61355,
                "uploadUrl": "http://files.zweitgeist.com/25/f4/9d/2bcef3b363f3bf7ec262461df58a3901c1.gif"
            }
        },
        "chat": {
            "chat": {
                "enabled": true,
                "isLoop": false,
                "probability": 1000,
                "finalFileName": "chat.gif",
                "packedFileName": "341733.gif",
                "uploadId": 341733,
                "uploadTime": "20080917155635",
                "uploadUserId": 93135,
                "uploadSize": 39510,
                "uploadUrl": "http://files.zweitgeist.com/3e/84/16/e4443300328e71598a019fa5e601599f47.gif"
            }
        },
        "agree": {
            "agree": {
                "enabled": true,
                "isLoop": false,
                "probability": 1000,
                "finalFileName": "agree.gif",
                "packedFileName": "341735.gif",
                "uploadId": 341735,
                "uploadTime": "20080917155644",
                "uploadUserId": 93135,
                "uploadSize": 25507,
                "uploadUrl": "http://files.zweitgeist.com/53/b7/b5/482b049633732cb719b95c6b985c66a55d.gif"
            }
        },
        "angry": {
            "angry": {
                "enabled": true,
                "isLoop": false,
                "probability": 1000,
                "finalFileName": "angry.gif",
                "packedFileName": "341736.gif",
                "uploadId": 341736,
                "uploadTime": "20080917155649",
                "uploadUserId": 93135,
                "uploadSize": 26796,
                "uploadUrl": "http://files.zweitgeist.com/c7/21/fd/0210acad8b94b814c3ae06027dfc6c6dcd.gif"
            }
        },
        "cheer": {
            "cheer": {
                "enabled": true,
                "isLoop": false,
                "probability": 1000,
                "finalFileName": "cheer.gif",
                "packedFileName": "341737.gif",
                "uploadId": 341737,
                "uploadTime": "20080917155654",
                "uploadUserId": 93135,
                "uploadSize": 60463,
                "uploadUrl": "http://files.zweitgeist.com/72/69/c0/1cd983d2be388090b47f0795477b5d1342.gif"
            }
        },
        "clap": {
            "clap": {
                "enabled": true,
                "isLoop": false,
                "probability": 1000,
                "finalFileName": "clap.gif",
                "packedFileName": "341738.gif",
                "uploadId": 341738,
                "uploadTime": "20080917155700",
                "uploadUserId": 93135,
                "uploadSize": 46333,
                "uploadUrl": "http://files.zweitgeist.com/5b/0c/dd/1cc260bc0a10d9593b38c33f85dd985e86.gif"
            }
        },
        "dance": {
            "dance": {
                "enabled": true,
                "isLoop": false,
                "probability": 500,
                "finalFileName": "dance.gif",
                "packedFileName": "341739.gif",
                "uploadId": 341739,
                "uploadTime": "20080917155705",
                "uploadUserId": 93135,
                "uploadSize": 149766,
                "uploadUrl": "http://files.zweitgeist.com/73/30/ea/f10eaa0daa6abd5f3efbb95d9c668e25c2.gif"
            }
        },
        "deny": {
            "deny": {
                "enabled": true,
                "isLoop": false,
                "probability": 1000,
                "finalFileName": "deny.gif",
                "packedFileName": "341740.gif",
                "uploadId": 341740,
                "uploadTime": "20080917155711",
                "uploadUserId": 93135,
                "uploadSize": 66437,
                "uploadUrl": "http://files.zweitgeist.com/63/2e/ff/610dd86bf5599f2336d04c8cce0e184ace.gif"
            }
        },
        "kiss": {
            "kiss": {
                "enabled": true,
                "isLoop": false,
                "probability": 1000,
                "finalFileName": "kiss.gif",
                "packedFileName": "341741.gif",
                "uploadId": 341741,
                "uploadTime": "20080917155717",
                "uploadUserId": 93135,
                "uploadSize": 68436,
                "uploadUrl": "http://files.zweitgeist.com/c3/33/12/134433d25d2688c0930ce1eb89a9a2c535.gif"
            }
        },
        "laugh": {
            "laugh": {
                "enabled": true,
                "isLoop": false,
                "probability": 1000,
                "finalFileName": "laugh.gif",
                "packedFileName": "341743.gif",
                "uploadId": 341743,
                "uploadTime": "20080917155721",
                "uploadUserId": 93135,
                "uploadSize": 56505,
                "uploadUrl": "http://files.zweitgeist.com/cc/3d/6f/7f62b1b24d302cc96fb1031f8952402c53.gif"
            }
        },
        "wave": {
            "wave": {
                "enabled": true,
                "isLoop": false,
                "probability": 1000,
                "finalFileName": "wave.gif",
                "packedFileName": "341744.gif",
                "uploadId": 341744,
                "uploadTime": "20080917155727",
                "uploadUserId": 93135,
                "uploadSize": 29063,
                "uploadUrl": "http://files.zweitgeist.com/b0/0d/84/bf34e3d31e45421e269322e00b27c021bb.gif"
            }
        },
        "yawn": {
            "yawn": {
                "enabled": true,
                "isLoop": false,
                "probability": 1000,
                "finalFileName": "yawn.gif",
                "packedFileName": "341745.gif",
                "uploadId": 341745,
                "uploadTime": "20080917155730",
                "uploadUserId": 93135,
                "uploadSize": 42273,
                "uploadUrl": "http://files.zweitgeist.com/5e/7c/7e/0c00ed43dd15e988ce78f9b4caa982aed8.gif"
            }
        },
        "moveleft": {
            "moveleft": {
                "enabled": true,
                "isLoop": true,
                "probability": 1000,
                "walkSpeed": 55,
                "finalFileName": "moveleft.gif",
                "packedFileName": "341746.gif",
                "uploadId": 341746,
                "uploadTime": "20080917155735",
                "uploadUserId": 93135,
                "uploadSize": 31109,
                "uploadUrl": "http://files.zweitgeist.com/96/e5/7a/ced4b292341cde413186bf4b5ffaeb4bba.gif"
            }
        },
        "moveright": {
            "moveright": {
                "enabled": true,
                "isLoop": true,
                "probability": 1000,
                "walkSpeed": 55,
                "finalFileName": "moveright.gif",
                "packedFileName": "341747.gif",
                "uploadId": 341747,
                "uploadTime": "20080917155739",
                "uploadUserId": 93135,
                "uploadSize": 25714,
                "uploadUrl": "http://files.zweitgeist.com/ab/5b/38/d0d8a5a7931e0fdea0349380e3ca6db004.gif"
            }
        }
    }
}
