{
    "avatarId": "SL439978",
    "avatarName": "SL 439978",
    "avatarSize": 100,
    "animationsGenerated": {
        "idle": {
            "idle": {
                "enabled": true,
                "isLoop": true,
                "probability": 1000,
                "finalFileName": "idle.gif",
                "packedFileName": "439960.gif",
                "uploadId": 439960,
                "uploadTime": "20090106115840",
                "uploadUserId": 1613397,
                "uploadSize": 4843,
                "uploadUrl": "http://files.zweitgeist.com/78/8d/a0/cc6ee90e036ff1ba61e2f0f455fc671a9e.gif"
            },
            "hands": {
                "enabled": true,
                "isLoop": false,
                "probability": 5,
                "finalFileName": "idle-hands.gif",
                "packedFileName": "439961.gif",
                "uploadId": 439961,
                "uploadTime": "20090106115842",
                "uploadUserId": 1613397,
                "uploadSize": 67229,
                "uploadUrl": "http://files.zweitgeist.com/0f/65/27/51c86a60584709532af9337571d93873be.gif"
            },
            "lookleft": {
                "enabled": true,
                "isLoop": false,
                "probability": 5,
                "finalFileName": "idle-lookleft.gif",
                "packedFileName": "439962.gif",
                "uploadId": 439962,
                "uploadTime": "20090106115844",
                "uploadUserId": 1613397,
                "uploadSize": 57987,
                "uploadUrl": "http://files.zweitgeist.com/ce/1c/dc/152a0f7a9ec454619a3e57f220472c58dc.gif"
            },
            "lookright": {
                "enabled": true,
                "isLoop": false,
                "probability": 5,
                "finalFileName": "idle-lookright.gif",
                "packedFileName": "439963.gif",
                "uploadId": 439963,
                "uploadTime": "20090106115845",
                "uploadUserId": 1613397,
                "uploadSize": 67554,
                "uploadUrl": "http://files.zweitgeist.com/e6/52/bc/33e0e36db428283d831c14497eae922e17.gif"
            }
        },
        "chat": {
            "chat": {
                "enabled": true,
                "isLoop": false,
                "probability": 1000,
                "finalFileName": "chat.gif",
                "packedFileName": "439964.gif",
                "uploadId": 439964,
                "uploadTime": "20090106115847",
                "uploadUserId": 1613397,
                "uploadSize": 47900,
                "uploadUrl": "http://files.zweitgeist.com/47/c6/6c/8d5cb2de86d32a07a1e1d7f595d70eb763.gif"
            }
        },
        "agree": {
            "agree": {
                "enabled": true,
                "isLoop": false,
                "probability": 1000,
                "finalFileName": "agree.gif",
                "packedFileName": "439966.gif",
                "uploadId": 439966,
                "uploadTime": "20090106115851",
                "uploadUserId": 1613397,
                "uploadSize": 67990,
                "uploadUrl": "http://files.zweitgeist.com/34/47/8d/c00486c38d548177ee23763dca33031836.gif"
            }
        },
        "angry": {
            "angry": {
                "enabled": true,
                "isLoop": false,
                "probability": 1000,
                "finalFileName": "angry.gif",
                "packedFileName": "439967.gif",
                "uploadId": 439967,
                "uploadTime": "20090106115852",
                "uploadUserId": 1613397,
                "uploadSize": 55453,
                "uploadUrl": "http://files.zweitgeist.com/aa/23/4e/c7c9227901ab7284848e498cac604802cd.gif"
            }
        },
        "cheer": {
            "cheer": {
                "enabled": true,
                "isLoop": false,
                "probability": 1000,
                "finalFileName": "cheer.gif",
                "packedFileName": "439968.gif",
                "uploadId": 439968,
                "uploadTime": "20090106115854",
                "uploadUserId": 1613397,
                "uploadSize": 45993,
                "uploadUrl": "http://files.zweitgeist.com/2c/44/71/50c21ac3399ef6427b899ae249ed308338.gif"
            }
        },
        "clap": {
            "clap": {
                "enabled": true,
                "isLoop": false,
                "probability": 1000,
                "finalFileName": "clap.gif",
                "packedFileName": "439970.gif",
                "uploadId": 439970,
                "uploadTime": "20090106115856",
                "uploadUserId": 1613397,
                "uploadSize": 53107,
                "uploadUrl": "http://files.zweitgeist.com/0a/69/2b/3bf3e6ab9026f47348bfb902dff2c4be3c.gif"
            }
        },
        "dance": {
            "dance": {
                "enabled": true,
                "isLoop": false,
                "probability": 500,
                "finalFileName": "dance.gif",
                "packedFileName": "439971.gif",
                "uploadId": 439971,
                "uploadTime": "20090106115857",
                "uploadUserId": 1613397,
                "uploadSize": 54099,
                "uploadUrl": "http://files.zweitgeist.com/c2/c3/18/0fa130abf7b1ede1cf732bb9d1686d93de.gif"
            }
        },
        "deny": {
            "deny": {
                "enabled": true,
                "isLoop": false,
                "probability": 1000,
                "finalFileName": "deny.gif",
                "packedFileName": "439972.gif",
                "uploadId": 439972,
                "uploadTime": "20090106115900",
                "uploadUserId": 1613397,
                "uploadSize": 54593,
                "uploadUrl": "http://files.zweitgeist.com/21/ab/0f/6b41664875fe2623e2161300d0ee60e85c.gif"
            }
        },
        "kiss": {
            "kiss": {
                "enabled": true,
                "isLoop": false,
                "probability": 1000,
                "finalFileName": "kiss.gif",
                "packedFileName": "439973.gif",
                "uploadId": 439973,
                "uploadTime": "20090106115902",
                "uploadUserId": 1613397,
                "uploadSize": 59113,
                "uploadUrl": "http://files.zweitgeist.com/31/7e/ab/8695536fa592a715abdc6a396de270eb62.gif"
            }
        },
        "laugh": {
            "laugh": {
                "enabled": true,
                "isLoop": false,
                "probability": 1000,
                "finalFileName": "laugh.gif",
                "packedFileName": "439974.gif",
                "uploadId": 439974,
                "uploadTime": "20090106115904",
                "uploadUserId": 1613397,
                "uploadSize": 47880,
                "uploadUrl": "http://files.zweitgeist.com/be/8a/1e/f862cfe48b27b36d19fb1ed87d01e60734.gif"
            }
        },
        "wave": {
            "wave": {
                "enabled": true,
                "isLoop": false,
                "probability": 1000,
                "finalFileName": "wave.gif",
                "packedFileName": "439975.gif",
                "uploadId": 439975,
                "uploadTime": "20090106115906",
                "uploadUserId": 1613397,
                "uploadSize": 72288,
                "uploadUrl": "http://files.zweitgeist.com/c0/48/22/3ee9f368027b18ae082e3c8cdfd4595aeb.gif"
            }
        },
        "yawn": {
            "yawn": {
                "enabled": true,
                "isLoop": false,
                "probability": 1000,
                "finalFileName": "yawn.gif",
                "packedFileName": "439976.gif",
                "uploadId": 439976,
                "uploadTime": "20090106115907",
                "uploadUserId": 1613397,
                "uploadSize": 49142,
                "uploadUrl": "http://files.zweitgeist.com/ef/77/32/a8d20b055dc4c0db26168e6b6f8a53b6e6.gif"
            }
        },
        "moveleft": {
            "moveleft": {
                "enabled": true,
                "isLoop": true,
                "probability": 1000,
                "walkSpeed": 55,
                "finalFileName": "moveleft.gif",
                "packedFileName": "439977.gif",
                "uploadId": 439977,
                "uploadTime": "20090106115909",
                "uploadUserId": 1613397,
                "uploadSize": 72550,
                "uploadUrl": "http://files.zweitgeist.com/dd/ed/ef/0a9a3a86bd733b72b491bfe5016fe1a703.gif"
            }
        },
        "moveright": {
            "moveright": {
                "enabled": true,
                "isLoop": true,
                "probability": 1000,
                "walkSpeed": 55,
                "finalFileName": "moveright.gif",
                "packedFileName": "439978.gif",
                "uploadId": 439978,
                "uploadTime": "20090106115911",
                "uploadUserId": 1613397,
                "uploadSize": 82783,
                "uploadUrl": "http://files.zweitgeist.com/37/24/cc/a8b7f01905611afdc02fa19fc3bb6d24ac.gif"
            }
        }
    }
}
