{
    "avatarId": "SL396736",
    "avatarName": "SL 396736",
    "avatarSize": 100,
    "animationsGenerated": {
        "idle": {
            "idle": {
                "enabled": true,
                "isLoop": true,
                "probability": 1000,
                "finalFileName": "idle.gif",
                "packedFileName": "396718.gif",
                "uploadId": 396718,
                "uploadTime": "20081124152733",
                "uploadUserId": 1613397,
                "uploadSize": 3604,
                "uploadUrl": "http://files.zweitgeist.com/ea/0f/c0/07718916f8f5aa4b077f62beb8b0543c11.gif"
            },
            "hands": {
                "enabled": true,
                "isLoop": false,
                "probability": 5,
                "finalFileName": "idle-hands.gif",
                "packedFileName": "396719.gif",
                "uploadId": 396719,
                "uploadTime": "20081124152735",
                "uploadUserId": 1613397,
                "uploadSize": 45211,
                "uploadUrl": "http://files.zweitgeist.com/97/a5/ba/91897ffd662cab0372975567bd0671b409.gif"
            },
            "lookleft": {
                "enabled": true,
                "isLoop": false,
                "probability": 5,
                "finalFileName": "idle-lookleft.gif",
                "packedFileName": "396720.gif",
                "uploadId": 396720,
                "uploadTime": "20081124152738",
                "uploadUserId": 1613397,
                "uploadSize": 38460,
                "uploadUrl": "http://files.zweitgeist.com/a4/66/47/656abebbb825c5d63ba8f2833b8d65c200.gif"
            },
            "lookright": {
                "enabled": true,
                "isLoop": false,
                "probability": 5,
                "finalFileName": "idle-lookright.gif",
                "packedFileName": "396721.gif",
                "uploadId": 396721,
                "uploadTime": "20081124152740",
                "uploadUserId": 1613397,
                "uploadSize": 48170,
                "uploadUrl": "http://files.zweitgeist.com/e6/2f/d7/26fb45f84bcf43e38303d87f1dfe02add7.gif"
            }
        },
        "chat": {
            "chat": {
                "enabled": true,
                "isLoop": false,
                "probability": 1000,
                "finalFileName": "chat.gif",
                "packedFileName": "396722.gif",
                "uploadId": 396722,
                "uploadTime": "20081124152743",
                "uploadUserId": 1613397,
                "uploadSize": 62375,
                "uploadUrl": "http://files.zweitgeist.com/7f/73/48/45d05801e3cee2951f4b4ff5bf2ce37084.gif"
            }
        },
        "agree": {
            "agree": {
                "enabled": true,
                "isLoop": false,
                "probability": 1000,
                "finalFileName": "agree.gif",
                "packedFileName": "396724.gif",
                "uploadId": 396724,
                "uploadTime": "20081124152747",
                "uploadUserId": 1613397,
                "uploadSize": 45524,
                "uploadUrl": "http://files.zweitgeist.com/66/0e/4e/234a523ee0b707c84fcf5d452b6efaa4b6.gif"
            }
        },
        "angry": {
            "angry": {
                "enabled": true,
                "isLoop": false,
                "probability": 1000,
                "finalFileName": "angry.gif",
                "packedFileName": "396725.gif",
                "uploadId": 396725,
                "uploadTime": "20081124152749",
                "uploadUserId": 1613397,
                "uploadSize": 43541,
                "uploadUrl": "http://files.zweitgeist.com/bb/8c/2d/3e19082021079559a22f41c2fa6a0d3cd9.gif"
            }
        },
        "cheer": {
            "cheer": {
                "enabled": true,
                "isLoop": false,
                "probability": 1000,
                "finalFileName": "cheer.gif",
                "packedFileName": "396726.gif",
                "uploadId": 396726,
                "uploadTime": "20081124152751",
                "uploadUserId": 1613397,
                "uploadSize": 63175,
                "uploadUrl": "http://files.zweitgeist.com/24/68/16/1ccf8a7193433875481fd0fdf577f34c9c.gif"
            }
        },
        "clap": {
            "clap": {
                "enabled": true,
                "isLoop": false,
                "probability": 1000,
                "finalFileName": "clap.gif",
                "packedFileName": "396727.gif",
                "uploadId": 396727,
                "uploadTime": "20081124152753",
                "uploadUserId": 1613397,
                "uploadSize": 35405,
                "uploadUrl": "http://files.zweitgeist.com/3f/7f/11/8822a81130cad39570230b20abb27ce6be.gif"
            }
        },
        "dance": {
            "dance": {
                "enabled": true,
                "isLoop": false,
                "probability": 500,
                "finalFileName": "dance.gif",
                "packedFileName": "396728.gif",
                "uploadId": 396728,
                "uploadTime": "20081124152755",
                "uploadUserId": 1613397,
                "uploadSize": 73315,
                "uploadUrl": "http://files.zweitgeist.com/1f/62/3c/41569be9fe4e18dfeb5921924d1afc0b19.gif"
            }
        },
        "deny": {
            "deny": {
                "enabled": true,
                "isLoop": false,
                "probability": 1000,
                "finalFileName": "deny.gif",
                "packedFileName": "396729.gif",
                "uploadId": 396729,
                "uploadTime": "20081124152757",
                "uploadUserId": 1613397,
                "uploadSize": 70931,
                "uploadUrl": "http://files.zweitgeist.com/74/b1/4a/a5532ca2343f3d4fe28f067a3a95a6e0a1.gif"
            }
        },
        "kiss": {
            "kiss": {
                "enabled": true,
                "isLoop": false,
                "probability": 1000,
                "finalFileName": "kiss.gif",
                "packedFileName": "396730.gif",
                "uploadId": 396730,
                "uploadTime": "20081124152759",
                "uploadUserId": 1613397,
                "uploadSize": 46234,
                "uploadUrl": "http://files.zweitgeist.com/6a/68/56/5c88102c544f3c06432bac8bc369132404.gif"
            }
        },
        "laugh": {
            "laugh": {
                "enabled": true,
                "isLoop": false,
                "probability": 1000,
                "finalFileName": "laugh.gif",
                "packedFileName": "396732.gif",
                "uploadId": 396732,
                "uploadTime": "20081124152802",
                "uploadUserId": 1613397,
                "uploadSize": 61701,
                "uploadUrl": "http://files.zweitgeist.com/1b/ac/db/d16eb4ed29dd0ef14554bbb052c99e2456.gif"
            }
        },
        "wave": {
            "wave": {
                "enabled": true,
                "isLoop": false,
                "probability": 1000,
                "finalFileName": "wave.gif",
                "packedFileName": "396733.gif",
                "uploadId": 396733,
                "uploadTime": "20081124152804",
                "uploadUserId": 1613397,
                "uploadSize": 48156,
                "uploadUrl": "http://files.zweitgeist.com/1b/a7/d5/396221dc95cb12510bbab15c0a2bbc1dac.gif"
            }
        },
        "yawn": {
            "yawn": {
                "enabled": true,
                "isLoop": false,
                "probability": 1000,
                "finalFileName": "yawn.gif",
                "packedFileName": "396734.gif",
                "uploadId": 396734,
                "uploadTime": "20081124152806",
                "uploadUserId": 1613397,
                "uploadSize": 64033,
                "uploadUrl": "http://files.zweitgeist.com/3b/18/32/39ea5f75861147d57006dd155fa6fc4a35.gif"
            }
        },
        "moveleft": {
            "moveleft": {
                "enabled": true,
                "isLoop": true,
                "probability": 1000,
                "walkSpeed": 55,
                "finalFileName": "moveleft.gif",
                "packedFileName": "396735.gif",
                "uploadId": 396735,
                "uploadTime": "20081124152808",
                "uploadUserId": 1613397,
                "uploadSize": 45741,
                "uploadUrl": "http://files.zweitgeist.com/db/8a/f4/2100b7b2aa772d2a3c31fe780a3661f593.gif"
            }
        },
        "moveright": {
            "moveright": {
                "enabled": true,
                "isLoop": true,
                "probability": 1000,
                "walkSpeed": 55,
                "finalFileName": "moveright.gif",
                "packedFileName": "396736.gif",
                "uploadId": 396736,
                "uploadTime": "20081124152810",
                "uploadUserId": 1613397,
                "uploadSize": 49795,
                "uploadUrl": "http://files.zweitgeist.com/89/0f/f1/fc01156e778abc8029fc1b730c8c2711ec.gif"
            }
        }
    }
}
